{
  "version": 2,
  "extractor": "papercropper",
  "tables": [
    {
      "url": "assets/tables/arxiv/2606.21884v1/table-001.webp",
      "caption": "",
      "page": 0,
      "index": 1,
      "width": 1124,
      "height": 561,
      "label": "Table"
    },
    {
      "url": "assets/tables/arxiv/2606.21884v1/table-002.webp",
      "caption": "",
      "page": 0,
      "index": 2,
      "width": 1333,
      "height": 478,
      "label": "Table"
    },
    {
      "url": "assets/tables/arxiv/2606.21884v1/table-003.webp",
      "caption": "",
      "page": 0,
      "index": 3,
      "width": 1537,
      "height": 326,
      "label": "Table"
    },
    {
      "url": "assets/tables/arxiv/2606.21884v1/table-004.webp",
      "caption": "",
      "page": 0,
      "index": 4,
      "width": 904,
      "height": 305,
      "label": "Table"
    },
    {
      "url": "assets/tables/arxiv/2606.21884v1/table-005.webp",
      "caption": "",
      "page": 0,
      "index": 5,
      "width": 1721,
      "height": 585,
      "label": "Table"
    },
    {
      "url": "assets/tables/arxiv/2606.21884v1/table-006.webp",
      "caption": "",
      "page": 0,
      "index": 6,
      "width": 1545,
      "height": 480,
      "label": "Table"
    },
    {
      "url": "assets/tables/arxiv/2606.21884v1/table-007.webp",
      "caption": "",
      "page": 0,
      "index": 7,
      "width": 992,
      "height": 244,
      "label": "Table"
    },
    {
      "url": "assets/tables/arxiv/2606.21884v1/table-008.webp",
      "caption": "",
      "page": 0,
      "index": 8,
      "width": 811,
      "height": 413,
      "label": "Table"
    },
    {
      "url": "assets/tables/arxiv/2606.21884v1/table-009.webp",
      "caption": "",
      "page": 0,
      "index": 9,
      "width": 1710,
      "height": 384,
      "label": "Table"
    },
    {
      "url": "assets/tables/arxiv/2606.21884v1/table-010.webp",
      "caption": "",
      "page": 0,
      "index": 10,
      "width": 790,
      "height": 497,
      "label": "Table"
    },
    {
      "url": "assets/tables/arxiv/2606.21884v1/table-011.webp",
      "caption": "",
      "page": 0,
      "index": 11,
      "width": 1540,
      "height": 504,
      "label": "Table"
    },
    {
      "url": "assets/tables/arxiv/2606.21884v1/table-012.webp",
      "caption": "",
      "page": 0,
      "index": 12,
      "width": 1217,
      "height": 585,
      "label": "Table"
    },
    {
      "url": "assets/tables/arxiv/2606.21884v1/table-013.webp",
      "caption": "",
      "page": 0,
      "index": 13,
      "width": 1204,
      "height": 1394,
      "label": "Table"
    },
    {
      "url": "assets/tables/arxiv/2606.21884v1/table-014.webp",
      "caption": "",
      "page": 0,
      "index": 14,
      "width": 736,
      "height": 371,
      "label": "Table"
    },
    {
      "url": "assets/tables/arxiv/2606.21884v1/table-015.webp",
      "caption": "",
      "page": 0,
      "index": 15,
      "width": 1161,
      "height": 416,
      "label": "Table"
    },
    {
      "url": "assets/tables/arxiv/2606.21884v1/table-016.webp",
      "caption": "",
      "page": 0,
      "index": 16,
      "width": 1137,
      "height": 330,
      "label": "Table"
    },
    {
      "url": "assets/tables/arxiv/2606.21884v1/table-017.webp",
      "caption": "",
      "page": 0,
      "index": 17,
      "width": 1317,
      "height": 563,
      "label": "Table"
    },
    {
      "url": "assets/tables/arxiv/2606.21884v1/table-018.webp",
      "caption": "",
      "page": 0,
      "index": 18,
      "width": 1463,
      "height": 501,
      "label": "Table"
    }
  ]
}